setup.py
wymypy/__init__.py
wymypy/wymypy.py
wymypy.egg-info/PKG-INFO
wymypy.egg-info/SOURCES.txt
wymypy.egg-info/dependency_links.txt
wymypy.egg-info/entry_points.txt
wymypy.egg-info/top_level.txt
wymypy/libs/__init__.py
wymypy/libs/common.py
wymypy/libs/config.py
wymypy/libs/dict4ini.py
wymypy/libs/mpdclient.py
wymypy/libs/mpdsafe.py
wymypy/libs/unittest.py
wymypy/libs/utilities.py
wymypy/libs/wsgiserver.py
wymypy/plugins/__init__.py
wymypy/plugins/library/__init__.py
wymypy/plugins/playlists/__init__.py
wymypy/plugins/search/__init__.py
