Metadata-Version: 1.0
Name: wymypy
Version: 1.2
Summary: WyMyPy is a standalone webserver music player frontend
Home-page: http://manatlan.infogami.com/wymypy
Author: marc lentz
Author-email: manatlan@gmail.com
License: UNKNOWN
Keywords: multimedia,webserver,mpd
Platform: UNKNOWN
